{
  "StorageAccount": "zukestorage3833",
  "PublicIP": "40.88.243.43",
  "GitHubRepo": "https://github.com/Vic3e-Digital/zuke-video-shorts-creator.git",
  "GitHubBranch": "main",
  "PublicURL": "http://zuke-video-4563.eastus.azurecontainer.io:8000",
  "VideoStorageURL": "https://zukestorage3833.blob.core.windows.net/video-content/",
  "ResourceGroup": "zuke-video-shorts-rg",
  "HealthCheck": "http://zuke-video-4563.eastus.azurecontainer.io:8000/",
  "FQDN": "zuke-video-4563.eastus.azurecontainer.io",
  "ContainerName": "zuke-video-processor",
  "Location": "East US",
  "DeployedAt": "2026-01-19T02:08:20.3748110+02:00",
  "APIEndpoint": "http://zuke-video-4563.eastus.azurecontainer.io:8000/process",
  "AcrServer": "zukevideoacr4089.azurecr.io",
  "AcrName": "zukevideoacr4089",
  "PrivateStorage": false,
  "BuildSource": "GitHub",
  "StorageContainer": "video-content"
}
